{
   "type":"origins:active_self",
   "entity_action":{
      "type":"origins:and",
      "actions":[
         {
            "type":"origins:if_else",
            "condition":{
               "type":"origins:resource",
               "resource":"quirks:acid/corrosive_liquid_resource",
               "comparison":">=",
               "compare_to":1
            },
            "if_action":{
               "type": "origins:choice",
               "actions": [
                   {
                       "element": {    
                        "type": "origins:modify_resource",
                        "modifier": {
                           "operation": "add_base_early",
                           "value": -1.00
                        },
                        "resource": "quirks:acid/corrosive_liquid_resource"
                       },
                       "weight": 20
                   },
                   {
                       "element": {
                        "type": "origins:modify_resource",
                        "modifier": {
                           "operation": "add_base_early",
                           "value": -2.00
                        },
                        "resource": "quirks:acid/corrosive_liquid_resource"
                       },
                       "weight": 20
                   }
               ]
            },
            "else_action":{
               "type": "origins:choice",
               "actions": [
                   {
                       "element": {    
                        "type":"origins:damage",
                        "amount":2,
                        "damage_type":"quirks:acid/acid_corrosion"
                       },
                       "weight": 20
                   },
                   {
                       "element": {
                        "type":"origins:damage",
                        "amount":3,
                        "damage_type":"quirks:acid/acid_corrosion"
                       },
                       "weight": 20
                   }
               ]
            }
         },
         {
            "type":"origins:play_sound",
            "sound":"minecraft:entity.cat.hiss",
            "category":"ambient",
            "volume":0.30,
            "pitch":2.00
         },
         {
            "type":"origins:execute_command",
            "command":"particle minecraft:sneeze ^ ^1 ^1.5 0.3 0.3 0.3 0.01 1"
         },
         {
            "type":"origins:execute_command",
            "command":"particle minecraft:spit ^ ^1 ^1.5 0.3 0.3 0.3 0.01 1"
         },
         {
            "type":"origins:execute_command",
            "command":"particle minecraft:sneeze ^ ^1 ^3 0.3 0.3 0.3 0.01 1"
         },
         {
            "type":"origins:execute_command",
            "command":"particle minecraft:spit ^ ^1 ^3 0.3 0.3 0.3 0.01 1"
         },
         {
            "type":"origins:spawn_entity",
            "entity_type":"minecraft:area_effect_cloud",
            "tag":"{Particle:\"effect\",Radius:1f,Duration:10,Color:1347973,Effects:[{Id:2,Amplifier:0b,Duration:80,ShowParticles:0b},{Id:18,Amplifier:0b,Duration:80,ShowParticles:0b},{Id:20,Amplifier:0b,Duration:80,ShowParticles:0b}]}",
            "entity_action":{
               "type":"origins:and",
               "actions":[
                  {
                     "type":"origins:execute_command",
                     "command":"tp @s ^ ^1 ^2.5"
                  },
                  {
                     "type":"origins:area_of_effect",
                     "radius":5.00,
                     "shape":"cube",
                     "bientity_action":{
                        "type":"origins:target_action",
                        "action":{
                           "type":"origins:and",
                           "actions":[
                              {
                                 "type":"origins:spawn_particles",
                                 "particle":"minecraft:sneeze",
                                 "count":10,
                                 "speed":0.18,
                                 "force":true,
                                 "spread":{
                                    "x":0.20,
                                    "y":0.20,
                                    "z":0.20
                                 },
                                 "offset_x":0.00,
                                 "offset_y":0.50,
                                 "offset_z":0.00
                              },
                              {
                                 "type":"origins:execute_command",
                                 "command":"kill @s"
                              },
                              {
                                 "type":"origins:play_sound",
                                 "sound":"minecraft:block.fire.extinguish",
                                 "volume":0.50,
                                 "pitch":2.00
                              }
                           ]
                        }
                     },
                     "bientity_condition":{
                        "type":"origins:target_condition",
                        "condition":{
                           "type":"origins:in_tag",
                           "tag":"minecraft:impact_projectiles"
                        }
                     },
                     "include_actor":false
                  }
               ]
            }
         },
         {
            "type":"origins:spawn_entity",
            "entity_type":"minecraft:area_effect_cloud",
            "tag":"{Particle:\"effect\",Radius:1f,Duration:10,Color:1347973,Effects:[{Id:2,Amplifier:0b,Duration:80,ShowParticles:0b},{Id:18,Amplifier:0b,Duration:80,ShowParticles:0b},{Id:20,Amplifier:0b,Duration:80,ShowParticles:0b}]}",
            "entity_action":{
               "type":"origins:and",
               "actions":[
                  {
                     "type":"origins:execute_command",
                     "command":"tp @s ^ ^1 ^4"
                  },
                  {
                     "type":"origins:area_of_effect",
                     "radius":5.00,
                     "shape":"cube",
                     "bientity_action":{
                        "type":"origins:target_action",
                        "action":{
                           "type":"origins:and",
                           "actions":[
                              {
                                 "type":"origins:spawn_particles",
                                 "particle":"minecraft:sneeze",
                                 "count":10,
                                 "speed":0.18,
                                 "force":true,
                                 "spread":{
                                    "x":0.20,
                                    "y":0.20,
                                    "z":0.20
                                 },
                                 "offset_x":0.00,
                                 "offset_y":0.50,
                                 "offset_z":0.00
                              },
                              {
                                 "type":"origins:execute_command",
                                 "command":"kill @s"
                              },
                              {
                                 "type":"origins:play_sound",
                                 "sound":"minecraft:block.fire.extinguish",
                                 "volume":0.50,
                                 "pitch":2.00
                              }
                           ]
                        }
                     },
                     "bientity_condition":{
                        "type":"origins:target_condition",
                        "condition":{
                           "type":"origins:in_tag",
                           "tag":"minecraft:impact_projectiles"
                        }
                     },
                     "include_actor":false
                  }
               ]
            }
         }
      ]
   },
   "cooldown":1,
   "hud_render":{
      "should_render":false
   },
   "key":{
      "key":"key.origins.secondary_active",
      "continuous":true
   },
   "condition": {
      "type": "origins:resource",
      "resource": "quirks:universal/quirk_erased",
      "comparison": "==",
      "compare_to": 0
   }
}